{
"registers": [
{
  "lat": 38.40,
  "log": 37.38,
  "place": "CENTRAL TURKEY",
  "magnitude": 2.6
},
{
  "lat": 16.48,
  "log": -94.53,
  "place": "OAXACA, MEXICO",
  "magnitude": 4.1
},
{
  "lat": -1.85,
  "log": 133.11,
  "place": "PAPUA, INDONESIA",
  "magnitude": 2.9
},
{
  "lat": -19.90,
  "log": -177.79,
  "place": "FIJI REGION",
  "magnitude": 4.7
},
{
  "lat": 37.47,
  "log": -118.85,
  "place": "CENTRAL CALIFORNIA",
  "magnitude": 2.2
},
{
  "lat": 39.86,
  "log": 41.13,
  "place": "EASTERN TURKEY",
  "magnitude": 2.3
},
{
  "lat": -7.91,
  "log": 117.66,
  "place": "BALI SEA",
  "magnitude": 3.6
},
{
  "lat": -34.52,
  "log": 178.46,
  "place": "SOUTH OF KERMADEC ISLANDS",
  "magnitude": 3.5
},
{
  "lat": 38.26,
  "log": 37.62,
  "place": "CENTRAL TURKEY",
  "magnitude": 2.1
},
{
  "lat": -31.99,
  "log": -71.65,
  "place": "OFFSHORE COQUIMBO, CHILE",
  "magnitude": 2.5
},
{
  "lat": 47.69,
  "log": 8.32,
  "place": "GERMANY",
  "magnitude": 1.2
},
{
  "lat": 38.48,
  "log": 37.56,
  "place": "CENTRAL TURKEY",
  "magnitude": 2.6
},
{
  "lat": 37.44,
  "log": 36.36,
  "place": "CENTRAL TURKEY",
  "magnitude": 2.2
},
{
  "lat": 39.34,
  "log": 40.48,
  "place": "EASTERN TURKEY",
  "magnitude": 2.2
},
{
  "lat": 46.80,
  "log": 6.37,
  "place": "FRANCE",
  "magnitude": 2.0
},
{
  "lat": 18.18,
  "log": -65.76,
  "place": "PUERTO RICO",
  "magnitude": 2.4
},
{
  "lat": 17.85,
  "log": -63.53,
  "place": "ST. MARTIN REGION, LEEWARD ISL.",
  "magnitude": 3.5
},
{
  "lat": -8.66,
  "log": 119.04,
  "place": "FLORES REGION, INDONESIA",
  "magnitude": 2.7
},
{
  "lat": 38.36,
  "log": 36.90,
  "place": "CENTRAL TURKEY",
  "magnitude": 2.6
},
{
  "lat": -4.34,
  "log": 140.42,
  "place": "PAPUA, INDONESIA",
  "magnitude": 2.7
},
{
  "lat": 39.03,
  "log": 40.45,
  "place": "EASTERN TURKEY",
  "magnitude": 2.1
},
{
  "lat": -31.96,
  "log": -71.66,
  "place": "OFFSHORE COQUIMBO, CHILE",
  "magnitude": 3.1
},
{
  "lat": 36.21,
  "log": 36.21,
  "place": "TURKEY-SYRIA BORDER REGION",
  "magnitude": 2.3
},
{
  "lat": 1.66,
  "log": 98.05,
  "place": "NORTHERN SUMATRA, INDONESIA",
  "magnitude": 2.6
},
{
  "lat": 44.24,
  "log": 10.39,
  "place": "NORTHERN ITALY",
  "magnitude": 2.4
},
{
  "lat": 17.95,
  "log": -66.96,
  "place": "PUERTO RICO",
  "magnitude": 2.8
},
{
  "lat": 38.04,
  "log": 37.63,
  "place": "CENTRAL TURKEY",
  "magnitude": 2.2
},
{
  "lat": 28.24,
  "log": -16.68,
  "place": "CANARY ISLANDS, SPAIN REGION",
  "magnitude": 1.6
},
{
  "lat": 18.79,
  "log": -64.25,
  "place": "VIRGIN ISLANDS REGION",
  "magnitude": 3.5
},
{
  "lat": -23.78,
  "log": -68.34,
  "place": "ANTOFAGASTA, CHILE",
  "magnitude": 2.8
},
{
  "lat": 47.74,
  "log": 6.90,
  "place": "FRANCE",
  "magnitude": 2.0
},
{
  "lat": 18.67,
  "log": -66.52,
  "place": "PUERTO RICO REGION",
  "magnitude": 2.8
},
{
  "lat": 18.04,
  "log": -66.81,
  "place": "PUERTO RICO",
  "magnitude": 2.0
},
{
  "lat": 19.41,
  "log": -155.24,
  "place": "ISLAND OF HAWAII, HAWAII",
  "magnitude": 2.2
},
{
  "lat": 37.89,
  "log": 36.31,
  "place": "CENTRAL TURKEY",
  "magnitude": 2.6
},
{
  "lat": -20.59,
  "log": -68.82,
  "place": "TARAPACA, CHILE",
  "magnitude": 4.5
},
{
  "lat": -37.20,
  "log": 177.42,
  "place": "OFF E. COAST OF N. ISLAND, N.Z.",
  "magnitude": 3.0
},
{
  "lat": 37.90,
  "log": 36.41,
  "place": "CENTRAL TURKEY",
  "magnitude": 2.3
},
{
  "lat": 36.03,
  "log": 26.96,
  "place": "DODECANESE ISLANDS, GREECE",
  "magnitude": 2.7
},
{
  "lat": 37.95,
  "log": 36.26,
  "place": "CENTRAL TURKEY",
  "magnitude": 2.8
},
{
  "lat": 17.79,
  "log": -68.52,
  "place": "DOMINICAN REPUBLIC REGION",
  "magnitude": 3.7
},
{
  "lat": 38.79,
  "log": -122.76,
  "place": "NORTHERN CALIFORNIA",
  "magnitude": 3.9
},
{
  "lat": 39.83,
  "log": 27.94,
  "place": "WESTERN TURKEY",
  "magnitude": 2.2
},
{
  "lat": 38.79,
  "log": -122.77,
  "place": "NORTHERN CALIFORNIA",
  "magnitude": 3.0
},
{
  "lat": 17.27,
  "log": -95.19,
  "place": "OAXACA, MEXICO",
  "magnitude": 4.0
},
{
  "lat": 37.81,
  "log": 37.81,
  "place": "CENTRAL TURKEY",
  "magnitude": 2.0
},
{
  "lat": 39.89,
  "log": 41.09,
  "place": "EASTERN TURKEY",
  "magnitude": 3.7
},
{
  "lat": 63.55,
  "log": -147.31,
  "place": "CENTRAL ALASKA",
  "magnitude": 2.5
},
{
  "lat": -23.99,
  "log": 179.97,
  "place": "SOUTH OF FIJI ISLANDS",
  "magnitude": 4.3
},
{
  "lat": 37.50,
  "log": 37.25,
  "place": "CENTRAL TURKEY",
  "magnitude": 2.3
}
]
}
