{
"registers": [
{
  "lat": 38.14,
  "log": 36.22,
  "place": "CENTRAL TURKEY",
  "magnitude": 2.9
},
{
  "lat": 39.98,
  "log": 20.63,
  "place": "GREECE",
  "magnitude": 2.1
},
{
  "lat": 19.40,
  "log": -155.26,
  "place": "ISLAND OF HAWAII, HAWAII",
  "magnitude": 2.1
},
{
  "lat": -18.47,
  "log": -177.94,
  "place": "FIJI REGION",
  "magnitude": 4.6
},
{
  "lat": 40.59,
  "log": -124.44,
  "place": "OFFSHORE NORTHERN CALIFORNIA",
  "magnitude": 2.5
},
{
  "lat": -31.65,
  "log": -71.87,
  "place": "OFFSHORE COQUIMBO, CHILE",
  "magnitude": 2.8
},
{
  "lat": -34.41,
  "log": -73.72,
  "place": "OFF COAST OF O&#39;HIGGINS, CHILE",
  "magnitude": 2.9
},
{
  "lat": 37.94,
  "log": 36.38,
  "place": "CENTRAL TURKEY",
  "magnitude": 2.8
},
{
  "lat": 44.54,
  "log": 149.38,
  "place": "KURIL ISLANDS",
  "magnitude": 4.8
},
{
  "lat": 33.12,
  "log": -116.53,
  "place": "SOUTHERN CALIFORNIA",
  "magnitude": 2.1
},
{
  "lat": 58.32,
  "log": -154.88,
  "place": "ALASKA PENINSULA",
  "magnitude": 2.5
},
{
  "lat": 19.23,
  "log": -155.38,
  "place": "ISLAND OF HAWAII, HAWAII",
  "magnitude": 2.1
},
{
  "lat": -9.17,
  "log": 124.16,
  "place": "TIMOR REGION",
  "magnitude": 3.6
},
{
  "lat": 12.05,
  "log": -87.87,
  "place": "NEAR COAST OF NICARAGUA",
  "magnitude": 2.6
},
{
  "lat": 38.46,
  "log": 40.39,
  "place": "EASTERN TURKEY",
  "magnitude": 2.7
},
{
  "lat": -35.86,
  "log": -73.46,
  "place": "OFFSHORE BIO-BIO, CHILE",
  "magnitude": 2.7
},
{
  "lat": 38.16,
  "log": 38.54,
  "place": "EASTERN TURKEY",
  "magnitude": 2.0
},
{
  "lat": 58.32,
  "log": -154.92,
  "place": "ALASKA PENINSULA",
  "magnitude": 2.8
},
{
  "lat": 38.15,
  "log": 37.97,
  "place": "CENTRAL TURKEY",
  "magnitude": 3.8
},
{
  "lat": 36.52,
  "log": 5.39,
  "place": "NORTHERN ALGERIA",
  "magnitude": 3.5
},
{
  "lat": 39.45,
  "log": 38.24,
  "place": "EASTERN TURKEY",
  "magnitude": 2.0
},
{
  "lat": -35.84,
  "log": -73.52,
  "place": "OFFSHORE BIO-BIO, CHILE",
  "magnitude": 3.2
},
{
  "lat": 37.77,
  "log": 36.44,
  "place": "CENTRAL TURKEY",
  "magnitude": 2.5
},
{
  "lat": 36.46,
  "log": 29.07,
  "place": "WESTERN TURKEY",
  "magnitude": 2.5
},
{
  "lat": -35.83,
  "log": -73.48,
  "place": "OFFSHORE BIO-BIO, CHILE",
  "magnitude": 3.6
},
{
  "lat": -7.56,
  "log": 114.03,
  "place": "BALI SEA",
  "magnitude": 2.9
},
{
  "lat": -35.85,
  "log": -71.52,
  "place": "MAULE, CHILE",
  "magnitude": 3.4
},
{
  "lat": 60.71,
  "log": -151.48,
  "place": "KENAI PENINSULA, ALASKA",
  "magnitude": 2.5
},
{
  "lat": -35.82,
  "log": -73.42,
  "place": "OFFSHORE BIO-BIO, CHILE",
  "magnitude": 3.7
},
{
  "lat": 12.08,
  "log": -86.65,
  "place": "NICARAGUA",
  "magnitude": 2.5
},
{
  "lat": 46.25,
  "log": 8.05,
  "place": "SWITZERLAND",
  "magnitude": 1.6
},
{
  "lat": 46.25,
  "log": 8.05,
  "place": "SWITZERLAND",
  "magnitude": 1.5
},
{
  "lat": -9.24,
  "log": 110.66,
  "place": "SOUTH OF JAVA, INDONESIA",
  "magnitude": 3.2
},
{
  "lat": 17.34,
  "log": -94.71,
  "place": "VERACRUZ, MEXICO",
  "magnitude": 4.0
},
{
  "lat": -32.60,
  "log": -71.64,
  "place": "OFFSHORE VALPARAISO, CHILE",
  "magnitude": 2.9
},
{
  "lat": -3.61,
  "log": 140.03,
  "place": "PAPUA, INDONESIA",
  "magnitude": 3.4
},
{
  "lat": 38.07,
  "log": 37.08,
  "place": "CENTRAL TURKEY",
  "magnitude": 3.1
},
{
  "lat": -35.75,
  "log": -73.44,
  "place": "OFFSHORE MAULE, CHILE",
  "magnitude": 3.2
},
{
  "lat": -2.62,
  "log": 101.79,
  "place": "SOUTHERN SUMATRA, INDONESIA",
  "magnitude": 2.9
},
{
  "lat": 37.92,
  "log": 36.22,
  "place": "CENTRAL TURKEY",
  "magnitude": 2.0
},
{
  "lat": -35.70,
  "log": -73.54,
  "place": "OFFSHORE MAULE, CHILE",
  "magnitude": 4.5
},
{
  "lat": -32.06,
  "log": 116.69,
  "place": "WESTERN AUSTRALIA",
  "magnitude": 2.1
},
{
  "lat": 42.27,
  "log": -124.28,
  "place": "OREGON",
  "magnitude": 2.3
},
{
  "lat": -11.26,
  "log": 118.44,
  "place": "SOUTH OF SUMBAWA, INDONESIA",
  "magnitude": 3.8
},
{
  "lat": 29.59,
  "log": 100.84,
  "place": "WESTERN SICHUAN, CHINA",
  "magnitude": 4.6
},
{
  "lat": 12.11,
  "log": -86.94,
  "place": "NICARAGUA",
  "magnitude": 2.6
},
{
  "lat": 6.94,
  "log": 123.62,
  "place": "MORO GULF, MINDANAO, PHILIPPINES",
  "magnitude": 4.7
},
{
  "lat": -20.84,
  "log": -69.18,
  "place": "TARAPACA, CHILE",
  "magnitude": 2.6
},
{
  "lat": 38.14,
  "log": 38.23,
  "place": "EASTERN TURKEY",
  "magnitude": 2.5
},
{
  "lat": 35.86,
  "log": -115.14,
  "place": "NEVADA",
  "magnitude": 2.0
}
]
}
